[
  {
    "id": "002",
    "title": "个人网站宣传视频",
    "author": "MrSunny",
    "date":"12-10,2021",
    "summary": "<p>闲来无事做的宣传片……<br>欢迎访问我的主页！<br>网址：https://mrsunny1008.github.io</p>",
    "sources": ["哔哩哔哩", "QQ空间"],
    "tags": ["哔哩哔哩", "QQ空间"],
    "url": "/blog/blog-宣传视频.html",
    "originUrl": "",
    "siderImg": "/assets/img/blog/sidder-cover/002.jpg",
    "coverImg": "/assets/img/blog/index-002.jpg"
  },
  {
    "id": "001",
    "title": "我的邀请邮件",
    "author": "MrSunny",
    "date":"11-13,2021",
    "summary": "<p>你好! 欢迎访问我的主页！<br>我是你的QQ好友MrSunny.我正通过邮件向你发送通知，以便于当我更换联系方式时…</p>",
    "sources": ["QQ邮箱"],
    "tags": ["QQ邮箱"],
    "url": "/blog/blog-我的邀请邮件.html",
    "originUrl": "",
    "siderImg": "/assets/img/blog/sidder-cover/001.jpg",
    "coverImg": "/assets/img/blog/index-001.jpg"
  },
        {
    "id": "003",
    "title": "【时光】程小时陆光钥匙挂件",
    "author": "MrSunny",
    "date":"08-14,2021",
    "summary": "<p><br><br></p>",
    "sources": ["哔哩哔哩"],
    "tags": ["哔哩哔哩"],
    "url": "https://www.bilibili.com/video/BV19M4y157QF?from=search&seid=8822461577805219835&spm_id_from=333.337.0.0",
    "originUrl": "https://www.bilibili.com/video/BV19M4y157QF?from=search&seid=8822461577805219835&spm_id_from=333.337.0.0",
    "siderImg": "/assets/img/blog/sidder-cover/003.jpg",
    "coverImg": "/assets/img/blog/index-000.jpg"
  },
          {
    "id": "004",
    "title": "【个人动态】CCTV6真的有工作细胞！！",
    "author": "MrSunny",
    "date":"07-18,2021",
    "summary": "<p><br><br></p>",
    "sources": ["哔哩哔哩"],
    "tags": ["哔哩哔哩"],
    "url": "https://www.bilibili.com/video/BV1QX4y1F7ti?from=search&seid=8822461577805219835&spm_id_from=333.337.0.0",
    "originUrl": "https://www.bilibili.com/video/BV1QX4y1F7ti?from=search&seid=8822461577805219835&spm_id_from=333.337.0.0",
    "siderImg": "/assets/img/blog/sidder-cover/004.jpg",
    "coverImg": "/assets/img/blog/index-000.jpg"
  },
    {
    "id": "005",
    "title": "【视频】<span>苏东双语初二⑸班青春纪念视频",
    "author": "MrSunny",
    "date":"06-15,2019",
    "summary": "<p>因为有你，青春无悔~！<br></p>",
    "sources": ["哔哩哔哩", "QQ空间"],
    "tags": ["哔哩哔哩", "QQ空间"],
    "url": "https://www.bilibili.com/video/BV1s4411V7hN?spm_id_from=333.999.0.0",
    "originUrl": "https://www.bilibili.com/video/BV1s4411V7hN?spm_id_from=333.999.0.0",
    "siderImg": "/assets/img/blog/sidder-cover/005.jpg",
    "coverImg": "/assets/img/blog/index-000.jpg"
  },
      {
    "id": "006",
    "title": "【闪光用户奖】全B站的人都在领奖，小透明明TM为我颁奖了！",
    "author": "MrSunny",
    "date":"01-29,2022",
    "summary": "<p><br><br></p>",
    "sources": ["哔哩哔哩"],
    "tags": ["哔哩哔哩"],
    "url": "https://www.bilibili.com/video/BV14P4y1N7jX/",
    "originUrl": "https://www.bilibili.com/video/BV14P4y1N7jX/",
    "siderImg": "/assets/img/blog/sidder-cover/006.jpg",
    "coverImg": "/assets/img/blog/index-000.jpg"
  },
    {
    "id": "007",
    "title": "湾湾媒体直播求关注，大陆网友：下次一定！！",
    "author": "MrSunny",
    "date":"08-07,2022",
    "summary": "<p>下次一定＞︿＜<br>-素材来源：YouTube 侵删</p>",
    "sources": ["哔哩哔哩"],
    "tags": ["哔哩哔哩"],
    "url": "https://www.bilibili.com/video/BV1jS4y147uh?spm_id_from=333.999.0.0&vd_source=e228ff6f18981e08df31565c90e77355",
    "originUrl": "https://www.bilibili.com/video/BV1jS4y147uh?spm_id_from=333.999.0.0&vd_source=e228ff6f18981e08df31565c90e77355",
    "siderImg": "/assets/img/blog/sidder-cover/002.jpg",
    "coverImg": "/assets/img/blog/index-000.jpg"
  },
    {
    "id": "008",
    "title": "植物大战僵尸2九周年祝福邮件",
    "author": "MrSunny",
    "date":"08-21,2022",
    "summary": "<p>在9周年即将到来之际<br>祝植物大战僵尸2<br>生日快乐</p>",
    "sources": ["QQ邮箱"],
    "tags": ["QQ邮箱"],
    "url": "/blog/blog-植物大战僵尸2九周年祝福邮件.html",
    "originUrl": "",
    "siderImg": "/assets/img/blog/sidder-cover/008.jpg",
    "coverImg": "/assets/img/blog/index-000.jpg"
  },
  {
    "id": "009",
    "title": "【推荐】Win11概念版光标",
    "author": "MrSunny",
    "date":"01-07,2023",
    "summary": "<p>网上看到这款鼠标指针，非常大气，<br>与Window11风格搭配十分好看。<br>转载自互联网。</p>",
    "sources": ["https://mrsunny.top"],
    "tags": ["https://mrsunny.top"],
    "url": "/blog/blog-推荐Windows11鼠标指针.html",
    "originUrl": "",
    "siderImg": "/assets/img/blog/sidder-cover/009.jpg",
    "coverImg": "/assets/img/blog/index-009.jpg"
  },
  {
    "id": "010",
    "title": "【分享】Edge儿童模式主题和壁纸",
    "author": "MrSunny",
    "date":"01-19,2023",
    "summary": "<p>众所周知，微软在2021年上线了儿童模式<br>儿童模式主题非常好看<br>提取了部分主题和壁纸</p>",
    "sources": ["https://mrsunny.top"],
    "tags": ["https://mrsunny.top"],
    "url": "/blog/blog-Edge儿童模式主题.html",
    "originUrl": "",
    "siderImg": "/assets/img/blog/sidder-cover/010.jpg",
    "coverImg": "/assets/img/blog/index-010.jpg"
  },

    {
    "id": "011",
    "title": "【自制】徐海学院原神风格创意Logo",
    "author": "MrSunny",
    "date":"11-21,2024",
    "summary": "<p>希望这份分享能点燃你的创意之火，<br>唤起同样热爱自由的心。<br>——原神，启动！！！</p>",
    "sources": ["https://mrsunny.top"],
    "tags": ["https://mrsunny.top"],
    "url": "/blog/blog-自制徐海学院原神风格Logo.html",
    "originUrl": "",
    "siderImg": "/assets/img/blog/sidder-cover/011.jpg",
    "coverImg": "/assets/img/blog/index-011.jpg"
  }
]
